cdk_cloudformation_newrelic_agent_configuration/__init__.py
cdk_cloudformation_newrelic_agent_configuration/py.typed
cdk_cloudformation_newrelic_agent_configuration/_jsii/__init__.py
cdk_cloudformation_newrelic_agent_configuration/_jsii/newrelic-agent-configuration@1.1.0-alpha.7.jsii.tgz
cdk_cloudformation_newrelic_agent_configuration-1.1.0a7.dist-info/LICENSE
cdk_cloudformation_newrelic_agent_configuration-1.1.0a7.dist-info/METADATA
cdk_cloudformation_newrelic_agent_configuration-1.1.0a7.dist-info/WHEEL
cdk_cloudformation_newrelic_agent_configuration-1.1.0a7.dist-info/top_level.txt
cdk_cloudformation_newrelic_agent_configuration-1.1.0a7.dist-info/RECORD
